cragmm_search/__init__.py
cragmm_search/search.py
cragmm_search/utils.py
cragmm_search/image_search_mock_api/__init__.py
cragmm_search/image_search_mock_api/generate_index.py
cragmm_search/image_search_mock_api/image_api.py
cragmm_search/image_search_mock_api/image_kg.py
cragmm_search/image_search_mock_api/image_search.py
cragmm_search/web_search_mock_api/__init__.py
cragmm_search/web_search_mock_api/generate_index.py
cragmm_search/web_search_mock_api/api/__init__.py
cragmm_search/web_search_mock_api/api/web_api.py
cragmm_search/web_search_mock_api/api/web_index.py
cragmm_search/web_search_mock_api/api/web_search.py
cragmm_search_pipeline-0.5.0.dist-info/LICENSE
cragmm_search_pipeline-0.5.0.dist-info/METADATA
cragmm_search_pipeline-0.5.0.dist-info/WHEEL
cragmm_search_pipeline-0.5.0.dist-info/top_level.txt
cragmm_search_pipeline-0.5.0.dist-info/RECORD
